{"timeStamp": 1645781385698, "stats": {"team": {"firstHalf": {"startTimeStamp": 0, "stats": {}}, "secondHalf": {"startTimeStamp": 0, "stats": {}}, "fullGame": {"startTimeStamp": 1645781375698, "stats": {"Normal": {"sprinting": {"amount": 0.0, "distance": 0.0}, "hiRunning": {"amount": 0.0, "distance": 0.0}, "running": {"amount": 0.0, "distance": 0.0}, "walking": {"amount": 0.0, "distance": 0.0}}, "XccStat": {"hiAcc": {"amount": 0.0, "distance": 0.0}, "midAcc": {"amount": 0.0, "distance": 0.0}, "lowAcc": {"amount": 0.0, "distance": 0.0}, "hiDec": {"amount": 0.0, "distance": 0.0}, "midDec": {"amount": 0.0, "distance": 0.0}, "lowDec": {"amount": 0.0, "distance": 0.0}}, "Distance": {"amount": 0.0, "distance": 0.0}, "Intensity": {"amount": 0.04, "distance": 0.0}}}, "drills": []}, "players": {"CC:1A:80:22": {"firstHalf": {"startTimeStamp": 0, "stats": {}}, "secondHalf": {"startTimeStamp": 0, "stats": {}}, "fullGame": {"startTimeStamp": 1645781375698, "stats": {"Normal": {"sprinting": {"amount": 0, "distance": 0}, "hiRunning": {"amount": 0, "distance": 0}, "running": {"amount": 0, "distance": 0}, "walking": {"amount": 0, "distance": 0}}, "XccStat": {"hiAcc": {"amount": 0, "distance": 0}, "midAcc": {"amount": 0, "distance": 0}, "lowAcc": {"amount": 0, "distance": 0}, "hiDec": {"amount": 0, "distance": 0}, "midDec": {"amount": 0, "distance": 0}, "lowDec": {"amount": 0, "distance": 0}}, "Distance": {"amount": 0, "distance": 0}, "Intensity": {"amount": 0.04, "distance": 0}}}, "drills": []}}}, "series": {"team": {"firstHalf": {"startTimeStamp": 0, "series": {}}, "secondHalf": {"startTimeStamp": 0, "series": {}}, "fullGame": {"startTimeStamp": 1645781375698, "series": {"acceleration": {"yLSeriesLow": [0.0], "yLSeriesMid": [0.0], "yLSeriesHigh": [0.0], "yLSeries": [0.0], "yRSeries": [0.0]}, "deceleration": {"yLSeriesLow": [0.0], "yLSeriesMid": [0.0], "yLSeriesHigh": [0.0], "yLSeries": [0.0], "yRSeries": [0.0]}, "sprints": {"yLSeries": [0.0], "yRSeries": [0.0]}, "HI": {"yLSeries": [0.0], "yRSeries": [0.0]}, "running": {"yLSeries": [0.0], "yRSeries": [0.0]}, "walking": {"yLSeries": [0.0], "yRSeries": [0.0]}, "distances": {"yLSeries": [0.0], "yRSeries": [0.0]}, "velocity": {"yLSeries": [0.0], "yRSeries": [0.0]}, "technical": {"yLSeries": [0.0], "yRSeries": [0.0]}, "intensity": {"yLSeries": [0.04], "yRSeries": [0.04]}}}, "drills": []}, "players": {"CC:1A:80:22": {"firstHalf": {"startTimeStamp": 0, "series": {}}, "secondHalf": {"startTimeStamp": 0, "series": {}}, "fullGame": {"startTimeStamp": 1645781375698, "series": {"acceleration": {"yLSeriesLow": [0], "yLSeriesMid": [0], "yLSeriesHigh": [0], "yLSeries": [0], "yRSeries": [0]}, "deceleration": {"yLSeriesLow": [0], "yLSeriesMid": [0], "yLSeriesHigh": [0], "yLSeries": [0], "yRSeries": [0]}, "sprints": {"yLSeries": [0], "yRSeries": [0]}, "HI": {"yLSeries": [0], "yRSeries": [0]}, "running": {"yLSeries": [0], "yRSeries": [0]}, "walking": {"yLSeries": [0], "yRSeries": [0]}, "distances": {"yLSeries": [0], "yRSeries": [0]}, "velocity": {"yLSeries": [0], "yRSeries": [0]}, "technical": {"yLSeries": [0], "yRSeries": [0]}, "intensity": {"yLSeries": [0.04], "yRSeries": [0.04]}}}, "drills": []}}}}
